sfwas/SFClans.py
sfwas/SFPlayer.py
sfwas/SFPlayerClan.py
sfwas/__init__.py
sfwas/supyfwa.py
sfwas/Base/__init__.py
sfwas/Base/abc.py
sfwas/Base/bases.py
sfwas/Base/exceptions.py
sfwas/Utils/Tags.py
sfwas/Utils/__init__.py
sfwas/Utils/enums.py
tests/testcase.py
supy_fwas-0.0.9.dist-info/LICENSE
supy_fwas-0.0.9.dist-info/METADATA
supy_fwas-0.0.9.dist-info/WHEEL
supy_fwas-0.0.9.dist-info/top_level.txt
supy_fwas-0.0.9.dist-info/RECORD
