Metadata-Version: 2.1
Name: supy-fwas
Version: 0.0.9
Summary: A wrapper library to easily retrieve FWA related information that is publicly available and free-to-use.
Author-email: Real-Supreme <botdevsupreme@gmail.com>
Project-URL: Homepage, https://github.com/real-supreme/supy-fwas
Project-URL: Bug Tracker, https://github.com/real-supreme/supy-fwas/issues
Classifier: Programming Language :: Python :: 3
Classifier: License :: OSI Approved :: MIT License
Classifier: Operating System :: OS Independent
Classifier: Development Status :: 4 - Beta
Classifier: Natural Language :: English
Classifier: Topic :: Internet
Classifier: Topic :: Software Development :: Libraries
Classifier: Topic :: Software Development :: Libraries :: Python Modules
Classifier: Topic :: Utilities
Requires-Python: >=3.7
License-File: LICENSE
